keyrings/__init__.py
keyrings/lastpass/__init__.py
keyrings/lastpass/cli.py
keyrings/lastpass/lpass.py
keyrings.lastpass-0.2.dist-info/LICENSE
keyrings.lastpass-0.2.dist-info/METADATA
keyrings.lastpass-0.2.dist-info/WHEEL
keyrings.lastpass-0.2.dist-info/entry_points.txt
keyrings.lastpass-0.2.dist-info/top_level.txt
keyrings.lastpass-0.2.dist-info/RECORD
